zlipy/__init__.py
zlipy/__main__.py
zlipy/api_client.py
zlipy/cli/__init__.py
zlipy/cli/app.py
zlipy/config/__init__.py
zlipy/config/configs.py
zlipy/config/constants.py
zlipy/config/factory.py
zlipy/config/interfaces.py
zlipy/config/utils.py
zlipy/domain/__init__.py
zlipy/domain/events/__init__.py
zlipy/domain/events/constants.py
zlipy/domain/events/events.py
zlipy/domain/events/factory.py
zlipy/domain/events/interfaces.py
zlipy/domain/filesfilter/__init__.py
zlipy/domain/filesfilter/constants.py
zlipy/domain/filesfilter/factory.py
zlipy/domain/filesfilter/filters.py
zlipy/domain/filesfilter/interfaces.py
zlipy/domain/filesfilter/loaders.py
zlipy/domain/tools/__init__.py
zlipy/domain/tools/interfaces.py
zlipy/domain/tools/load.py
zlipy/domain/tools/search.py
zlipy/services/__init__.py
zlipy/services/api/__init__.py
zlipy/services/api/clients.py
zlipy/services/api/constants.py
zlipy/services/api/factory.py
zlipy/services/api/interfaces.py
zlipy/services/client/__init__.py
zlipy/services/client/clients.py
zlipy/services/client/factory.py
zlipy/services/client/interfaces.py
zlipy/services/console/__init__.py
zlipy/services/console/loading_animation.py
zlipy/services/console/print.py
zlipy/services/console/ublock_tty.py
zlipy/services/embeddings.py
zlipy/services/errors_handler/__init__.py
zlipy/services/errors_handler/handler.py
zlipy/services/errors_handler/utils.py
zlipy/services/handlers/__init__.py
zlipy/services/handlers/handlers.py
zlipy-0.2.7.dist-info/METADATA
zlipy-0.2.7.dist-info/WHEEL
zlipy-0.2.7.dist-info/entry_points.txt
zlipy-0.2.7.dist-info/RECORD
